{
  "title": "SPIDER-MAN: BRAND NEW DAY – Final Trailer (Peter’s Journey) 4K",
  "duration_seconds": 157,
  "description": "It's about to be a Brand New Day. Get tickets now.\n\n#SpiderManBrandNewDay is in theatres July 31. \n\nIt's a BRAND NEW DAY for Peter Parker. Fighting crime full-time as Spider-Man in a world that doesn’t remember him—and the pressure of seeing his old friends move on without him—sparks a change in Peter he may not have the power to control. But that transformation might also be the only thing that can stop a shocking new threat to the city and those he loves - a powerful villain no one can even see.\n \nThe world may have forgotten Peter Parker, but he hasn’t forgotten them.\n\n► SUBSCRIBE to the channel to get notified when new Marvel videos are posted: https://www.youtube.com/marvel?sub_confirmation=1\n\n► SUBSCRIBE to Disney+ to stream all of your favorite Marvel shows and movies: https://www.disneyplus.com/\n\nFollow on social media to get the latest news and announcements from Marvel:\n\nTikTok: https://www.tiktok.com/@marvel\nInstagram: https://www.instagram.com/marvel\nFacebook: https://www.facebook.com/Marvel\nX: https://x.com/marvel\n\nExperience more stories by subscribing: \n\n@Disney \n@StarWars \n@pixar \n@disneyplus",
  "transcript": "Hi, my name is Peter Parker. I have something to tell you that's going [music] to sound crazy. But, it's the truth. >> You're the Spider-Man. >> You can't tell anybody about this. Can you keep it a secret? >> Okay. >> Thank you. Everybody good? >> Yeah, Spider-Man. >> We used to know each other. >> [music] >> We were together. But, something bad was going to happen. Me. And the only way to stop it [music] was to do the hard thing. You're going to forget who I am. >> What? >> What are you talking about? >> I'm going to come and find you. And [music] I'll explain everything. >> You better. I love you. I love you. Just wait until [music] me when you see me again. >> My name is Peter Parker and I I like a coffee. >> Is there anything [music] else? >> Maybe I'll never read this to you. >> No. >> Maybe I'm just writing this for me. And maybe that's my responsibility to live alone with the truth. Because I'm not just Peter Parker. I'm Spider-Man. >> When [music] faced with a threat that can be anyone. >> You sure you want to do this, Scorpion? >> You think I'm Scorpion? >> Talk to Banner? >> No Banner. Only Hulk. >> I'm sorry for you in danger. >> I'm sorry for your inconvenience. >> you that I would keep you safe. Please, you just have to trust me. Come on. >> Fine. >> You're the only one who can sense it. >> [music] >> Hey, can we do this one at a time, please? >> You're the only one who can defeat it. >> [music] >> The Spidey Tracker app says that Spider-Man is in the direct vicinity. >> Oh, yeah? No way, that's crazy.",
  "video_id": "daXaTug8rL4",
  "source_url": "https://www.youtube.com/watch?v=daXaTug8rL4"
}
